{
	"authors" :
	[ 
		{ "key"     : "me",
	      "name"  	: "Tobias Dürschmid",
	    },
		{ "key"     : "MT",
	      "name"  	: "Matthias Trapp",
	      "website" : "https://hpi.de/en/doellner/people/current/trapp.html",
	      "note" 	: "Matthias Trapp is senior researcher at the computer graphics group at the Hasso Plattner Institute.",
	  	},
	  	{ "key"     : "JD"	,
	      "name"  	: "Jürgen Döllner",
	      "website" : "https://hpi.de/en/doellner/",
	      "note" 	: "Jürgen Döllner is professor at the computer graphics group at the Hasso Plattner Institute.",
	  	},
	  	{ "key"     : "AS"	,
	      "name"  	: "Amir Semmo",
	      "website" : "http://asemmo.github.io/",
	      "note" 	: "Amir Semmo is postdoc at the computer graphics group at the Hasso Plattner Institute.",
	  	},
	  	{ "key"     : "SP"	,
	      "name"  	: "Sebastian Pasewaldt",
	      "website" : "https://hpi.de/doellner/people/current/pasewaldt.html",
	      "note" 	: "Amir Semmo is postdoc at the computer graphics group at the Hasso Plattner Institute.",
	  	},
	  	{ "key"     : "MS"	,
	      "name"  	: "Maximilian Söchting",
	      "website" : "http://msoechting.de/",
	  	},
	  	{ "key"     : "MK"	,
	      "name"  	: "Mandy Klingbeil",
	      "website" : "https://hpi.de/doellner/people/current/mandy-klingbeil.html",
	  	},
	  	{ "key"     : "Thijs"	,
	      "name"  	: "Thijs Roumen",
	      "website" : "http://thijsroumen.eu/",
	  	},
	  	{ "key"     : "PB"	,
	      "name"  	: "Patrick Baudisch",
	      "website" : "http://www.patrickbaudisch.com/",
	  	},
	  	{ "key"     : "TobiasNack"	,
	      "name"  	: "Tobias Nack",
	  	},
	  	{ "key"     : "pre"	,
	      "name"  	: "Patrick Rein",
	      "website" : "http://patrickrein.de/",
	      "note" 	: "Patrick Rein is a PhD student at the software architecture group at the Hasso Plattner Institute.",
	  	},
	  	{ "key"     : "RH"	,
	      "name"  	: "Robert Hirschfeld",
	      "website" : "http://hirschfeld.org/",
	      "note" 	: "Robert Hirschfeld is professor at the software architecture group at the Hasso Plattner Institute.",
	  	},
	  	{ "key"     : "MarcelTaeumel"	,
	      "name"  	: "Marcel Taeumel",
	      "website" : "http://taeumel.eu/",
	      "note" 	: "Marcel Taeumel is a PhD student at the software architecture group at the Hasso Plattner Institute.",
	  	}
	]
}
